memara/__init__.py
memara/client.py
memara/exceptions.py
memara/models.py
memara-0.2.0.dist-info/licenses/LICENSE
tests/__init__.py
tests/test_client.py
memara-0.2.0.dist-info/METADATA
memara-0.2.0.dist-info/WHEEL
memara-0.2.0.dist-info/top_level.txt
memara-0.2.0.dist-info/RECORD
