Metadata-Version: 2.4
Name: memara
Version: 0.2.0
Summary: Official Python SDK for the Memara API - Give your AI a perfect memory
Home-page: https://memara.io
Author: Memara Team
Author-email: Memara Team <hello@memara.io>
License-Expression: MIT
Project-URL: Homepage, https://memara.io
Project-URL: Documentation, https://memara.io/docs
Project-URL: Repository, https://github.com/memara-ai/memara-python-sdk
Project-URL: Bug Tracker, https://github.com/memara-ai/memara-python-sdk/issues
Project-URL: Changelog, https://github.com/memara-ai/memara-python-sdk/blob/main/CHANGELOG.md
Keywords: ai,memory,api,sdk,artificial-intelligence,llm,gpt,claude
Classifier: Development Status :: 4 - Beta
Classifier: Intended Audience :: Developers
Classifier: Operating System :: OS Independent
Classifier: Programming Language :: Python :: 3
Classifier: Programming Language :: Python :: 3.9
Classifier: Programming Language :: Python :: 3.10
Classifier: Programming Language :: Python :: 3.11
Classifier: Programming Language :: Python :: 3.12
Classifier: Topic :: Software Development :: Libraries :: Python Modules
Classifier: Topic :: Scientific/Engineering :: Artificial Intelligence
Classifier: Topic :: Internet :: WWW/HTTP :: Dynamic Content
Requires-Python: >=3.9
License-File: LICENSE
Requires-Dist: httpx>=0.24.0
Requires-Dist: pydantic>=2.0.0
Provides-Extra: dev
Requires-Dist: pytest>=7.4.0; extra == "dev"
Requires-Dist: pytest-cov>=4.1.0; extra == "dev"
Requires-Dist: black>=23.7.0; extra == "dev"
Requires-Dist: mypy>=1.4.1; extra == "dev"
Requires-Dist: isort>=5.12.0; extra == "dev"
Requires-Dist: httpx[dev]>=0.24.0; extra == "dev"
Dynamic: author
Dynamic: home-page
Dynamic: license-file
Dynamic: requires-python
